raztint/__init__.py
raztint/colors.py
raztint/icons.py
raztint/raztint.py
raztint-0.1.1.dist-info/METADATA
raztint-0.1.1.dist-info/WHEEL
raztint-0.1.1.dist-info/licenses/LICENSE
raztint-0.1.1.dist-info/RECORD
