Metadata-Version: 2.4
Name: raztint
Version: 0.1.1
Summary: A zero-dependency Python library for ANSI coloring and smart CLI icons with automatic environment detection
Project-URL: Homepage, https://github.com/razbuild/raztint
Project-URL: Documentation, https://github.com/razbuild/raztint#readme
Project-URL: Repository, https://github.com/razbuild/raztint
Project-URL: Issues, https://github.com/razbuild/raztint/issues
Project-URL: Changelog, https://github.com/razbuild/raztint/releases
Author-email: Raz <real.raz.dev@gmail.com>
Maintainer-email: Raz <real.raz.dev@gmail.com>
License: MIT
License-File: LICENSE
Keywords: ansi,cli,color,colour,console,cross-platform,icons,nerd-fonts,terminal,terminal-colors,text-coloring
Classifier: Development Status :: 5 - Production/Stable
Classifier: Intended Audience :: Developers
Classifier: License :: OSI Approved :: MIT License
Classifier: Operating System :: OS Independent
Classifier: Programming Language :: Python
Classifier: Programming Language :: Python :: 3
Classifier: Programming Language :: Python :: 3.13
Classifier: Topic :: Software Development :: Libraries :: Python Modules
Classifier: Topic :: System :: Systems Administration
Classifier: Topic :: Terminals
Classifier: Topic :: Utilities
Classifier: Typing :: Typed
Requires-Python: >=3.13
Provides-Extra: coverage
Requires-Dist: coverage; extra == 'coverage'
Requires-Dist: pytest-cov; extra == 'coverage'
Provides-Extra: dev
Requires-Dist: black; extra == 'dev'
Requires-Dist: coverage; extra == 'dev'
Requires-Dist: mypy; extra == 'dev'
Requires-Dist: pytest; extra == 'dev'
Requires-Dist: pytest-cov; extra == 'dev'
Requires-Dist: ruff; extra == 'dev'
Provides-Extra: formatter
Requires-Dist: black; extra == 'formatter'
Provides-Extra: lint
Requires-Dist: ruff; extra == 'lint'
Provides-Extra: test
Requires-Dist: pytest; extra == 'test'
Requires-Dist: pytest-cov; extra == 'test'
Provides-Extra: typecheck
Requires-Dist: mypy; extra == 'typecheck'
